{
  "wireMagic": "pb3",
  "pens": [ {
  
  } ],
  "wsWinStyles": [ {
  
  } ],
  "wpWinPositions": [ {
  
  } ],
  "events": [ {
    "tStartMs": 8900,
    "dDurationMs": 2800,
    "segs": [ {
      "utf8": "There is a family near Salzburg"
    } ]
  }, {
    "tStartMs": 11700,
    "dDurationMs": 2740,
    "segs": [ {
      "utf8": "that needs a governess until September."
    } ]
  }, {
    "tStartMs": 14440,
    "dDurationMs": 1960,
    "segs": [ {
      "utf8": "- Until September?\n- To take care of seven children."
    } ]
  }, {
    "tStartMs": 16900,
    "dDurationMs": 1120,
    "segs": [ {
      "utf8": "Seven children?!"
    } ]
  }, {
    "tStartMs": 18020,
    "dDurationMs": 1820,
    "segs": [ {
      "utf8": "Come out of that water at once!"
    } ]
  }, {
    "tStartMs": 20260,
    "dDurationMs": 1520,
    "segs": [ {
      "utf8": "Do you like children, Maria?"
    } ]
  }, {
    "tStartMs": 22180,
    "dDurationMs": 1880,
    "segs": [ {
      "utf8": "Oh, yes but seven!"
    } ]
  }, {
    "tStartMs": 24900,
    "dDurationMs": 3360,
    "segs": [ {
      "utf8": "I will tell Captain Von Trapp to expect you tomorrow."
    } ]
  }, {
    "tStartMs": 29560,
    "dDurationMs": 740,
    "segs": [ {
      "utf8": "Captain?"
    } ]
  }, {
    "tStartMs": 31420,
    "dDurationMs": 2240,
    "segs": [ {
      "utf8": "A retired officer of the Imperial Navy"
    } ]
  }, {
    "tStartMs": 33660,
    "dDurationMs": 1920,
    "segs": [ {
      "utf8": "a fine man and a brave one."
    } ]
  }, {
    "tStartMs": 36120,
    "dDurationMs": 2900,
    "segs": [ {
      "utf8": "Tell me, do you think the captain will get me some more material if I asked him?"
    } ]
  }, {
    "tStartMs": 39680,
    "dDurationMs": 1840,
    "segs": [ {
      "utf8": "How many dresses does a governess need?"
    } ]
  }, {
    "tStartMs": 41520,
    "dDurationMs": 1160,
    "segs": [ {
      "utf8": "Not for me, for the children."
    } ]
  }, {
    "tStartMs": 43520,
    "dDurationMs": 1620,
    "segs": [ {
      "utf8": "I want to make them some play clothes."
    } ]
  }, {
    "tStartMs": 45840,
    "dDurationMs": 2480,
    "segs": [ {
      "utf8": "The Von Trapp children don't play, they march."
    } ]
  }, {
    "tStartMs": 50200,
    "dDurationMs": 1660,
    "segs": [ {
      "utf8": "- But they‘re children!\n- Yes."
    } ]
  }, {
    "tStartMs": 52540,
    "dDurationMs": 1200,
    "segs": [ {
      "utf8": "And I'm their father."
    } ]
  }, {
    "tStartMs": 54980,
    "dDurationMs": 760,
    "segs": [ {
      "utf8": "Goodnight."
    } ]
  }, {
    "tStartMs": 66780,
    "dDurationMs": 2640,
    "segs": [ {
      "utf8": "Do you mean to tell me that my children"
    } ]
  }, {
    "tStartMs": 69420,
    "dDurationMs": 2280,
    "segs": [ {
      "utf8": "have been roaming about Salzburg"
    } ]
  }, {
    "tStartMs": 71700,
    "dDurationMs": 2400,
    "segs": [ {
      "utf8": "dressed up in nothing but some old drapes?"
    } ]
  }, {
    "tStartMs": 75060,
    "dDurationMs": 1920,
    "segs": [ {
      "utf8": "And having a marvellous time!"
    } ]
  }, {
    "tStartMs": 77780,
    "dDurationMs": 3860,
    "segs": [ {
      "utf8": "Fraulein, are you this much trouble at the Abby?"
    } ]
  }, {
    "tStartMs": 81800,
    "dDurationMs": 1400,
    "segs": [ {
      "utf8": "Oh, much more, Sir!"
    } ]
  }, {
    "tStartMs": 85880,
    "dDurationMs": 1560,
    "segs": [ {
      "utf8": "Why did they send you back to us?"
    } ]
  }, {
    "tStartMs": 87860,
    "dDurationMs": 1920,
    "segs": [ {
      "utf8": "They didn't send me back, Mother, I left."
    } ]
  }, {
    "tStartMs": 90580,
    "dDurationMs": 2240,
    "segs": [ {
      "utf8": "Is it true fraulein Maria isn‘t coming back?"
    } ]
  }, {
    "tStartMs": 93480,
    "dDurationMs": 1280,
    "segs": [ {
      "utf8": "I can‘t face him again."
    } ]
  }, {
    "tStartMs": 95820,
    "dDurationMs": 2380,
    "segs": [ {
      "utf8": "There's nothing more irresistible to a man"
    } ]
  }, {
    "tStartMs": 98200,
    "dDurationMs": 1540,
    "segs": [ {
      "utf8": "than a woman who‘s in love with him."
    } ]
  }, {
    "tStartMs": 99940,
    "dDurationMs": 1000,
    "segs": [ {
      "utf8": "In love with him?"
    } ]
  }, {
    "tStartMs": 101220,
    "dDurationMs": 2220,
    "segs": [ {
      "utf8": "Of course. What makes it so nice is"
    } ]
  }, {
    "tStartMs": 103440,
    "dDurationMs": 1940,
    "segs": [ {
      "utf8": "he thinks he's in love with you."
    } ]
  }, {
    "tStartMs": 107060,
    "dDurationMs": 2060,
    "segs": [ {
      "utf8": "There were times when we would look at each other..."
    } ]
  }, {
    "tStartMs": 109540,
    "dDurationMs": 1560,
    "segs": [ {
      "utf8": "Oh, Mother, I could hardly breathe."
    } ]
  }, {
    "tStartMs": 112420,
    "dDurationMs": 1180,
    "segs": [ {
      "utf8": "Are you in love with him?"
    } ]
  }, {
    "tStartMs": 114020,
    "dDurationMs": 2060,
    "segs": [ {
      "utf8": "I never felt that way before."
    } ]
  }, {
    "tStartMs": 116560,
    "dDurationMs": 960,
    "segs": [ {
      "utf8": "Maria."
    } ]
  }, {
    "tStartMs": 117760,
    "dDurationMs": 2540,
    "segs": [ {
      "utf8": "You have to live the life you were born to live."
    } ]
  }, {
    "tStartMs": 124360,
    "dDurationMs": 1540,
    "segs": [ {
      "utf8": "Somewhere out there"
    } ]
  }, {
    "tStartMs": 126280,
    "dDurationMs": 1780,
    "segs": [ {
      "utf8": "there‘s a young lady who I think"
    } ]
  }, {
    "tStartMs": 128600,
    "dDurationMs": 1460,
    "segs": [ {
      "utf8": "will never be a nun."
    } ]
  } ]
}
